{
    "sport_name": "123123123",
    "check_point": {
        "checkBox_right_elbow_flag": {
            "angle": 148.62008913750677,
            "state": false
        },
        "checkBox_right_shoulder_flag": {
            "angle": 150.2474012252539,
            "state": false
        },
        "checkBox_left_elbow_flag": {
            "angle": 99.91252368887561,
            "state": false
        },
        "checkBox_left_shoulder_flag": {
            "angle": 112.18615627300886,
            "state": true
        },
        "checkBox_left_hip_flag": {
            "angle": 65.17993850531036,
            "state": true
        },
        "checkBox_right_hip_flag": {
            "angle": 60.543489590696026,
            "state": true
        },
        "checkBox_left_knee_flag": {
            "angle": 83.028366426259,
            "state": false
        },
        "checkBox_right_knee_flag": {
            "angle": 93.68781206110071,
            "state": false
        }
    }
}